README.md
setup.py
ysc2/__init__.py
ysc2/utils/__init__.py
ysc2/utils/ipfs/__init__.py
ysc2/utils/ipfs/addresses.py
ysc2/utils/ipfs/apihelper.py
ysc2/utils/ipfs/file.py
ysc2/utils/ipfs/pubsub.py
ysc2/utils/rsa/__init__.py
ysc2/utils/rsa/helper.py
ysc2/utils/rsa/mutrades.py
ysc2/utils/rsa/openssl.py
ysc2/utils/rsa/origin.py
ysc2/utils/rsa/trade.py
ysc2_sdk.egg-info/PKG-INFO
ysc2_sdk.egg-info/SOURCES.txt
ysc2_sdk.egg-info/dependency_links.txt
ysc2_sdk.egg-info/requires.txt
ysc2_sdk.egg-info/top_level.txt