Metadata-Version: 2.1
Name: ysc2-sdk
Version: 0.0.4
Summary: A simple API for Yeaosound Chain
Home-page: https://gitlab.yeaosound.com/yeaosound/ysc/public/ysc-sdk-python
Author: Yang
Author-email: yangruoyu000@live.com
Classifier: Programming Language :: Python :: 3
Classifier: Operating System :: OS Independent
Provides-Extra: OpenSSL
